numerical_analysis/__init__.py
numerical_analysis/dependencies/__init__.py
numerical_analysis/dependencies/geometry.py
numerical_analysis/dependencies/polynomial.py
numerical_analysis/integration/__init__.py
numerical_analysis/integration/integration.py
numerical_analysis/interpolation/__init__.py
numerical_analysis/interpolation/interpolation.py
numerical_analysis/regression/__init__.py
numerical_analysis/regression/regression.py
numerical_analysis/root_finding/__init__.py
numerical_analysis/root_finding/root_finding.py
numerical_analysis/splines/__init__.py
numerical_analysis/splines/bezier.py
numerical_analysis/splines/composite_bezier.py
numerical_analysis-0.1.1.dist-info/LICENSE
numerical_analysis-0.1.1.dist-info/METADATA
numerical_analysis-0.1.1.dist-info/WHEEL
numerical_analysis-0.1.1.dist-info/top_level.txt
numerical_analysis-0.1.1.dist-info/RECORD
